MANIFEST.in
setup.cfg
setup.py
mkdocs_jinks/__init__.py
mkdocs_jinks.egg-info/PKG-INFO
mkdocs_jinks.egg-info/SOURCES.txt
mkdocs_jinks.egg-info/dependency_links.txt
mkdocs_jinks.egg-info/entry_points.txt
mkdocs_jinks.egg-info/top_level.txt
mkdocs_jinks/jinks_en/__init__.py
mkdocs_jinks/jinks_en/base.html
mkdocs_jinks/jinks_en/nav.html
mkdocs_jinks/jinks_en/search.html
mkdocs_jinks/jinks_en/css/darkula.css
mkdocs_jinks/jinks_en/css/theme.css
mkdocs_jinks/jinks_en/font/yekan.eot
mkdocs_jinks/jinks_en/font/yekan.ttf
mkdocs_jinks/jinks_en/font/yekan.woff
mkdocs_jinks/jinks_en/font/yekannumbers-regular.ttf
mkdocs_jinks/jinks_en/font/eot/IRANSansWeb.eot
mkdocs_jinks/jinks_en/font/eot/IRANSansWeb_Bold.eot
mkdocs_jinks/jinks_en/font/eot/IRANSansWeb_Light.eot
mkdocs_jinks/jinks_en/font/eot/IRANSansWeb_Medium.eot
mkdocs_jinks/jinks_en/font/eot/IRANSansWeb_UltraLight.eot
mkdocs_jinks/jinks_en/font/ttf/IRANSansWeb.ttf
mkdocs_jinks/jinks_en/font/ttf/IRANSansWeb_Bold.ttf
mkdocs_jinks/jinks_en/font/ttf/IRANSansWeb_Light.ttf
mkdocs_jinks/jinks_en/font/ttf/IRANSansWeb_Medium.ttf
mkdocs_jinks/jinks_en/font/ttf/IRANSansWeb_UltraLight.ttf
mkdocs_jinks/jinks_en/font/woff/IRANSansWeb.woff
mkdocs_jinks/jinks_en/font/woff/IRANSansWeb_Bold.woff
mkdocs_jinks/jinks_en/font/woff/IRANSansWeb_Light.woff
mkdocs_jinks/jinks_en/font/woff/IRANSansWeb_Medium.woff
mkdocs_jinks/jinks_en/font/woff/IRANSansWeb_UltraLight.woff
mkdocs_jinks/jinks_en/image/search-icon-fullsize.png
mkdocs_jinks/jinks_en/image/search-icon.png
mkdocs_jinks/jinks_en/js/highlight.pack.js
mkdocs_jinks/jinks_en/js/theme.js
mkdocs_jinks/jinks_fa/__init__.py
mkdocs_jinks/jinks_fa/base.html
mkdocs_jinks/jinks_fa/nav.html
mkdocs_jinks/jinks_fa/search.html
mkdocs_jinks/jinks_fa/css/darkula.css
mkdocs_jinks/jinks_fa/css/theme.css
mkdocs_jinks/jinks_fa/font/droidkufi/DroidKufi-Bold.eot
mkdocs_jinks/jinks_fa/font/droidkufi/DroidKufi-Bold.ttf
mkdocs_jinks/jinks_fa/font/droidkufi/DroidKufi-Bold.woff
mkdocs_jinks/jinks_fa/font/droidkufi/DroidKufi-Regular.eot
mkdocs_jinks/jinks_fa/font/droidkufi/DroidKufi-Regular.ttf
mkdocs_jinks/jinks_fa/font/droidkufi/DroidKufi-Regular.woff
