Metadata-Version: 1.0
Name: mkdocs-jinks
Version: 0.1.1
Summary: Jinks themes for MkDocs
Home-page: https://github.com/anetwork/mkdocs-jinks-theme
Author: Anetwork Technical Team
Author-email: dev@anetwork.io
License: BSD
Platform: UNKNOWN
